snit/__init__.py
snit/archive.py
snit/cli.py
snit-0.1.1.dist-info/entry_points.txt
snit-0.1.1.dist-info/WHEEL
snit-0.1.1.dist-info/METADATA
snit-0.1.1.dist-info/RECORD
