Metadata-Version: 2.1
Name: snit
Version: 0.1.1
Summary: Python command line application to backup IDE / code editor settings. 
Home-page: https://github.com/normanlorrain/snit
License: MIT
Author: Norman Lorrain
Author-email: normanlorrain@gmail.com
Requires-Python: >=3.9,<4.0
Classifier: License :: OSI Approved :: MIT License
Classifier: Programming Language :: Python :: 3
Classifier: Programming Language :: Python :: 3.9
Classifier: Topic :: Software Development
Requires-Dist: click (>=8.0.1,<9.0.0)
Project-URL: Repository, https://github.com/normanlorrain/snit
